graph/__init__.py
graph/bar diagram.py
graph/circle.py
graph/line draw.py
graph/point plot.py
LineGraph-0.0.1.dist-info/LICENCE
LineGraph-0.0.1.dist-info/METADATA
LineGraph-0.0.1.dist-info/WHEEL
LineGraph-0.0.1.dist-info/top_level.txt
LineGraph-0.0.1.dist-info/RECORD
