Metadata-Version: 2.1
Name: LineGraph
Version: 0.0.1
Summary: Some of the graphing practice with python
Home-page: https://github.com/Malay1998/GRAPH
Author: MALAY JYOTI DEBNATH
Author-email: malayjyotidebnath1@gmail.com
License: UNKNOWN
Project-URL: Bug Tracker, https://github.com/Malay1998/GRAPH/issues
Platform: UNKNOWN
Classifier: Programming Language :: Python :: 3
Classifier: License :: OSI Approved :: MIT License
Classifier: Operating System :: OS Independent
Requires-Python: >=3.6
License-File: LICENCE
